rvgeocoder/__init__.py
rvgeocoder/cKDTree_MP.py
rvgeocoder/rg_cities1000.csv
rvgeocoder-1.0.7.dist-info/LICENSE
rvgeocoder-1.0.7.dist-info/METADATA
rvgeocoder-1.0.7.dist-info/WHEEL
rvgeocoder-1.0.7.dist-info/top_level.txt
rvgeocoder-1.0.7.dist-info/RECORD
