Metadata-Version: 2.1
Name: rvgeocoder
Version: 1.0.7
Summary: Offline reverse geocoder
Home-page: https://github.com/sefiit/rvgeocoder
Author: Sefi Itzkovich
Author-email: sefi.itzkovich@gmail.com
License: lgpl
Platform: UNKNOWN
Requires-Dist: numpy (>=1.16.0)
Requires-Dist: scipy (>=1.3.0)
Requires-Dist: shapely (>=1.6.4.post2)
